mcp_cybersec_watchdog-0.1.0.dist-info/licenses/LICENSE
mcp_security/__init__.py
mcp_security/audit.py
mcp_security/constants.py
mcp_security/profile_weights.py
mcp_security/server.py
mcp_security/analyzers/__init__.py
mcp_security/analyzers/base.py
mcp_security/analyzers/cis.py
mcp_security/analyzers/cis_helpers.py
mcp_security/analyzers/containers.py
mcp_security/analyzers/cve.py
mcp_security/analyzers/disk.py
mcp_security/analyzers/docker_sec.py
mcp_security/analyzers/fail2ban.py
mcp_security/analyzers/filesystem.py
mcp_security/analyzers/firewall.py
mcp_security/analyzers/kernel.py
mcp_security/analyzers/mac.py
mcp_security/analyzers/network.py
mcp_security/analyzers/nist.py
mcp_security/analyzers/pci.py
mcp_security/analyzers/rootkit.py
mcp_security/analyzers/services.py
mcp_security/analyzers/ssh.py
mcp_security/analyzers/ssl.py
mcp_security/analyzers/sudoers.py
mcp_security/analyzers/system_hardening.py
mcp_security/analyzers/threats.py
mcp_security/analyzers/updates.py
mcp_security/analyzers/users.py
mcp_security/analyzers/webheaders.py
mcp_security/data/__init__.py
mcp_security/data/analysis_rules.yaml
mcp_security/monitoring/__init__.py
mcp_security/monitoring/anomaly.py
mcp_security/monitoring/baseline.py
mcp_security/monitoring/bulletin.py
mcp_security/monitoring/daemon.py
mcp_security/monitoring/manager.py
mcp_security/utils/__init__.py
mcp_security/utils/analyzer_registry.py
mcp_security/utils/command.py
mcp_security/utils/config.py
mcp_security/utils/detect.py
mcp_security/utils/logger.py
mcp_security/utils/permissions.py
mcp_security/utils/privacy.py
mcp_security/utils/rules_loader.py
mcp_cybersec_watchdog-0.1.0.dist-info/METADATA
mcp_cybersec_watchdog-0.1.0.dist-info/WHEEL
mcp_cybersec_watchdog-0.1.0.dist-info/entry_points.txt
mcp_cybersec_watchdog-0.1.0.dist-info/top_level.txt
mcp_cybersec_watchdog-0.1.0.dist-info/RECORD
