Metadata-Version: 2.4
Name: mcp-cybersec-watchdog
Version: 0.1.0
Summary: Cybersecurity monitoring and analysis for Linux servers via MCP
Author-email: Girste <me@girste.com>
License-Expression: MIT
Project-URL: Homepage, https://github.com/girste/mcp-cybersec-watchdog
Project-URL: Repository, https://github.com/girste/mcp-cybersec-watchdog
Project-URL: Issues, https://github.com/girste/mcp-cybersec-watchdog/issues
Keywords: mcp,security,audit,linux,server
Classifier: Development Status :: 3 - Alpha
Classifier: Intended Audience :: System Administrators
Classifier: Programming Language :: Python :: 3
Classifier: Programming Language :: Python :: 3.10
Classifier: Programming Language :: Python :: 3.11
Classifier: Programming Language :: Python :: 3.12
Requires-Python: >=3.10
License-File: LICENSE
Requires-Dist: mcp>=1.0.0
Requires-Dist: pyyaml>=6.0
Provides-Extra: dev
Requires-Dist: pytest>=7.4.0; extra == "dev"
Requires-Dist: pytest-cov>=4.1.0; extra == "dev"
Requires-Dist: pytest-asyncio>=0.21.0; extra == "dev"
Requires-Dist: black>=23.0.0; extra == "dev"
Requires-Dist: ruff>=0.1.0; extra == "dev"
Dynamic: license-file
